bizai/framework/__init__.py
bizai/framework/__pycache__/__init__.cpython-38.pyc
bizai/framework/constants/persistencevolumeenum.py
bizai/framework/constants/__pycache__/persistencevolumeenum.cpython-38.pyc
bizai/framework/decorators/__init__.py
bizai/framework/decorators/transactioncontext.py
bizai/framework/decorators/validate.py
bizai/framework/decorators/__pycache__/__init__.cpython-38.pyc
bizai/framework/decorators/__pycache__/transactioncontext.cpython-38.pyc
bizai/framework/decorators/__pycache__/validate.cpython-38.pyc
bizai/framework/persistence/__init__.py
bizai/framework/persistence/persistencevolume.py
bizai/framework/persistence/__pycache__/__init__.cpython-38.pyc
bizai/framework/persistence/__pycache__/client.cpython-38.pyc
bizai/framework/persistence/__pycache__/persistencevolume.cpython-38.pyc
bizai/framework/persistence/impl/__init__.py
bizai/framework/persistence/impl/db2persistence.py
bizai/framework/persistence/impl/ibmcospersistence.py
bizai/framework/services/__init__.py
bizai/framework/services/bizaimanager.py
bizai/framework/services/stepexecutor.py
bizai/framework/services/__pycache__/__init__.cpython-38.pyc
bizai/framework/services/__pycache__/bizaimanager.cpython-38.pyc
bizai/framework/services/__pycache__/invoker.cpython-38.pyc
bizai/framework/services/__pycache__/newrequeststepexecutor.cpython-38.pyc
bizai/framework/services/__pycache__/requestmanager.cpython-38.pyc
bizai/framework/services/__pycache__/requestmanagerimpl.cpython-38.pyc
bizai/framework/services/__pycache__/stepexecutor.cpython-38.pyc
bizai/framework/services/__pycache__/validate.cpython-38.pyc
bizai/framework/services/impl/__init__.py
bizai/framework/services/impl/invokersvc.py
bizai/framework/services/impl/persistencesvc.py
bizai/framework/services/impl/requestmanagersvc.py
bizai/framework/utils/__init__.py
bizai/framework/utils/app_enums.py
bizai/framework/utils/attachment.py
bizai/framework/utils/commonutils.py
bizai/framework/utils/confluent_kafka_producer.py
arunwagle_bizai_framework-0.0.6.dist-info/LICENSE
arunwagle_bizai_framework-0.0.6.dist-info/METADATA
arunwagle_bizai_framework-0.0.6.dist-info/WHEEL
arunwagle_bizai_framework-0.0.6.dist-info/top_level.txt
arunwagle_bizai_framework-0.0.6.dist-info/RECORD
